spatialproteomics/__init__.py
spatialproteomics/base_logger.py
spatialproteomics/constants.py
spatialproteomics/container.py
spatialproteomics/image_container/ImageContainer.py
spatialproteomics/image_container/__init__.py
spatialproteomics/la/__init__.py
spatialproteomics/la/label.py
spatialproteomics/la/utils.py
spatialproteomics/nh/__init__.py
spatialproteomics/nh/neighborhood.py
spatialproteomics/nh/utils.py
spatialproteomics/pl/__init__.py
spatialproteomics/pl/plot.py
spatialproteomics/pl/utils.py
spatialproteomics/pp/__init__.py
spatialproteomics/pp/intensity.py
spatialproteomics/pp/preprocessing.py
spatialproteomics/pp/utils.py
spatialproteomics/sd/__init__.py
spatialproteomics/sd/utils.py
spatialproteomics/tl/__init__.py
spatialproteomics/tl/tool.py
spatialproteomics/tl/utils.py
spatialproteomics-0.7.7.dist-info/licenses/LICENSE
spatialproteomics-0.7.7.dist-info/METADATA
spatialproteomics-0.7.7.dist-info/WHEEL
spatialproteomics-0.7.7.dist-info/top_level.txt
spatialproteomics-0.7.7.dist-info/RECORD
