Metadata-Version: 2.4
Name: spatialproteomics
Version: 0.7.7
Summary: Spatialproteomics is an interoperable toolbox for analyzing highly multiplexed fluorescence image data
Author: Matthias Meyer-Bender, Harald Vohringer
Requires-Python: >=3.10
License-File: LICENSE
Requires-Dist: cffi>=1.15.0
Requires-Dist: xarray>=2024.0.0
Requires-Dist: scikit-image>=0.25
Requires-Dist: matplotlib>=3.8.0
Requires-Dist: tqdm>=4.64.0
Requires-Dist: scikit-learn>=1.4.2
Requires-Dist: zarr>=2.0.0
Requires-Dist: numpy>=1.23
Requires-Dist: opencv-python>=4.11.0
Requires-Dist: pyyaml>=6.0
Provides-Extra: docs
Requires-Dist: Sphinx>=7.0.0; extra == "docs"
Requires-Dist: sphinx-book-theme>=0.0.39; extra == "docs"
Requires-Dist: sphinxcontrib-napoleon==0.7; extra == "docs"
Requires-Dist: nbsphinx>=0.9; extra == "docs"
Requires-Dist: sphinx-multiversion>=0.2.4; extra == "docs"
Requires-Dist: IPython>=8.0.0; extra == "docs"
Provides-Extra: spatialdata
Requires-Dist: spatialdata>=0.4.0; extra == "spatialdata"
Provides-Extra: cellpose
Requires-Dist: cellpose>=3.1.0; extra == "cellpose"
Provides-Extra: stardist
Requires-Dist: stardist>=0.9.1; extra == "stardist"
Provides-Extra: anndata
Requires-Dist: anndata; extra == "anndata"
Provides-Extra: astir
Requires-Dist: astir>=0.1.5; extra == "astir"
Provides-Extra: dev
Requires-Dist: pytest>=7.1.2; extra == "dev"
Requires-Dist: pytest-cov>=3.0.0; extra == "dev"
Requires-Dist: black[jupyter]>=22.6.0; extra == "dev"
Requires-Dist: isort>=5.10.1; extra == "dev"
Requires-Dist: flake8>=5.0.4; extra == "dev"
Requires-Dist: bandit>=1.7.4; extra == "dev"
Requires-Dist: safety>=2.1.1; extra == "dev"
Provides-Extra: all
Requires-Dist: spatialdata; extra == "all"
Requires-Dist: cellpose; extra == "all"
Requires-Dist: stardist; extra == "all"
Requires-Dist: astir; extra == "all"
Dynamic: license-file
